Metadata-Version: 2.4
Name: neuron_v0.4
Version: 0.4.91
Summary: A local AI assistant with OpenLLaMA and Mistral models, advanced identity protection and hardware optimization
Home-page: https://github.com/devpatel/neuron-ai-assistant
Author: Dev Patel
Author-email: devpatel@gmail.com
License: MIT
Project-URL: Bug Tracker, https://github.com/devpatel/neuron-ai-assistant/issues
Project-URL: Documentation, https://github.com/devpatel/neuron-ai-assistant/wiki
Project-URL: Source Code, https://github.com/devpatel/neuron-ai-assistant
Keywords: ai,assistant,chatbot,llm,language-model,openllama,mistral,transformers,local-ai,privacy,cuda,pytorch
Classifier: Development Status :: 4 - Beta
Classifier: Intended Audience :: Developers
Classifier: Intended Audience :: Science/Research
Classifier: Intended Audience :: End Users/Desktop
Classifier: Topic :: Scientific/Engineering :: Artificial Intelligence
Classifier: Topic :: Software Development :: Libraries :: Python Modules
Classifier: Topic :: Communications :: Chat
Classifier: License :: OSI Approved :: MIT License
Classifier: Programming Language :: Python :: 3
Classifier: Programming Language :: Python :: 3.8
Classifier: Programming Language :: Python :: 3.9
Classifier: Programming Language :: Python :: 3.10
Classifier: Programming Language :: Python :: 3.11
Classifier: Programming Language :: Python :: 3.12
Classifier: Operating System :: OS Independent
Classifier: Operating System :: POSIX :: Linux
Classifier: Operating System :: Microsoft :: Windows
Classifier: Operating System :: MacOS
Classifier: Environment :: Console
Classifier: Environment :: GPU :: NVIDIA CUDA
Classifier: Natural Language :: English
Requires-Python: >=3.8
License-File: License
Requires-Dist: torch>=2.0.0
Requires-Dist: transformers>=4.30.0
Requires-Dist: psutil>=5.9.0
Requires-Dist: cryptography>=41.0.0
Requires-Dist: huggingface-hub>=0.16.0
Provides-Extra: huggingface
Requires-Dist: huggingface-hub>=0.16.0; extra == "huggingface"
Provides-Extra: dev
Requires-Dist: pytest>=7.4.0; extra == "dev"
Requires-Dist: pytest-cov>=4.1.0; extra == "dev"
Requires-Dist: black>=23.0.0; extra == "dev"
Requires-Dist: flake8>=6.0.0; extra == "dev"
Requires-Dist: mypy>=1.4.0; extra == "dev"
Requires-Dist: isort>=5.12.0; extra == "dev"
Provides-Extra: all
Requires-Dist: huggingface-hub>=0.16.0; extra == "all"
Dynamic: author
Dynamic: author-email
Dynamic: classifier
Dynamic: description
Dynamic: description-content-type
Dynamic: home-page
Dynamic: keywords
Dynamic: license
Dynamic: license-file
Dynamic: project-url
Dynamic: provides-extra
Dynamic: requires-dist
Dynamic: requires-python
Dynamic: summary
